nc2csv/__init__.py
nc2csv/__main__.py
nc2csv/cli.py
nc2csv/nc2csv.py
nc2csv-0.1.2.dist-info/LICENSE
nc2csv-0.1.2.dist-info/METADATA
nc2csv-0.1.2.dist-info/WHEEL
nc2csv-0.1.2.dist-info/entry_points.txt
nc2csv-0.1.2.dist-info/top_level.txt
nc2csv-0.1.2.dist-info/RECORD
