Metadata-Version: 2.1
Name: nc2csv
Version: 0.1.2
Summary: Dump NetCDF file to CSV
Home-page: https://github.com/5tefan/nc2csv
Author: Stefan Codrescu
Author-email: ssmmcc1@gmail.com
Classifier: Development Status :: 4 - Beta
Classifier: Intended Audience :: Science/Research
Classifier: License :: OSI Approved :: MIT License
Classifier: Operating System :: OS Independent
License-File: LICENSE
Requires-Dist: Click
Requires-Dist: xarray
Requires-Dist: netcdf4
